CHANGELOG.txt
MANIFEST.in
setup.py
PostgresTools/__init__.py
PostgresTools.egg-info/PKG-INFO
PostgresTools.egg-info/SOURCES.txt
PostgresTools.egg-info/dependency_links.txt
PostgresTools.egg-info/top_level.txt
eqm.egg-info/SOURCES.txt
eqm.egg-info/dependency_links.txt
eqm.egg-info/top_level.txt