Metadata-Version: 1.1
Name: PostgresTools
Version: 0.0.7
Summary: Tools to copy database
Home-page: UNKNOWN
Author: Rafael Cardoso
Author-email: rmcardoso@outlook.com.br
License: MIT
Keywords: PostgresTools
Platform: UNKNOWN
Classifier: Development Status :: 5 - Production/Stable
Classifier: Intended Audience :: Education
Classifier: Operating System :: Microsoft :: Windows :: Windows 10
Classifier: License :: OSI Approved :: MIT License
Classifier: Programming Language :: Python :: 3
